basking/__init__.py
basking/basking_sdk.py
basking/constant.py
basking/graphql_query.py
basking/insight.py
basking/location.py
basking/occupancy.py
basking/organization.py
basking/queries.py
basking/user.py
basking/utils.py
basking_sdk-0.9.57.dist-info/LICENSE
basking_sdk-0.9.57.dist-info/METADATA
basking_sdk-0.9.57.dist-info/WHEEL
basking_sdk-0.9.57.dist-info/top_level.txt
basking_sdk-0.9.57.dist-info/RECORD
