Metadata-Version: 2.1
Name: basking-sdk
Version: 0.9.57
Summary: Basking.io python SDK
Home-page: https://basking.io
Author: Basking Automation GmbH
Author-email: info@basking.io
License: Copyright © 2022 Basking Automation GmbH
Project-URL: Homepage, https://basking.io
Keywords: occupancy analytics data api bas basking basking.io
Classifier: Programming Language :: Python :: 3
Classifier: Programming Language :: Python :: 3.7
Classifier: Programming Language :: Python :: 3.8
Classifier: Programming Language :: Python :: 3.9
Classifier: License :: OSI Approved :: MIT License
Classifier: Operating System :: OS Independent
Requires-Python: >=3.7, <4
License-File: LICENSE
Requires-Dist: backoff (>=2.0.0)
Requires-Dist: boto3 (>=1.0.0)
Requires-Dist: botocore (>=1.0.0)
Requires-Dist: certifi
Requires-Dist: charset-normalizer
Requires-Dist: graphqlclient (>=0.2.0)
Requires-Dist: idna
Requires-Dist: jmespath
Requires-Dist: numpy
Requires-Dist: pandas (>=1.0.0)
Requires-Dist: python-dateutil (>=2.0.0)
Requires-Dist: pytz
Requires-Dist: requests (>=2.0.0)
Requires-Dist: s3transfer
Requires-Dist: six
Requires-Dist: urllib3
